analyzer
apps
